dataprepro/__init__.py
dataprepro-0.1.0.dist-info/METADATA
dataprepro-0.1.0.dist-info/WHEEL
dataprepro-0.1.0.dist-info/top_level.txt
dataprepro-0.1.0.dist-info/RECORD
