Metadata-Version: 2.4
Name: dataprepro
Version: 0.1.0
Summary: Perform basic data pre-processing tasks such as handling missing values and outliers.
Author: Aryan Bhagwat
Author-email: legendasur531@gmail.com
Classifier: Programming Language :: Python :: 3
Classifier: Operating System :: OS Independent
Requires-Python: >=3.6
Dynamic: author
Dynamic: author-email
Dynamic: classifier
Dynamic: requires-python
Dynamic: summary
